pelmanism/__init__.py
pelmanism/bg.png
pelmanism/empty.png
pelmanism/pelmanism.py
pelmanism/cards/ball.png
pelmanism/cards/ballon.png
pelmanism/cards/baum.png
pelmanism/cards/berge.png
pelmanism/cards/birne.png
pelmanism/cards/blume.png
pelmanism/cards/brunnen.png
pelmanism/cards/burg.png
pelmanism/cards/drachen.png
pelmanism/cards/eis.png
pelmanism/cards/eismann.png
pelmanism/cards/ente.png
pelmanism/cards/fabrik.png
pelmanism/cards/fahne.png
pelmanism/cards/gewitter.png
pelmanism/cards/hammer.png
pelmanism/cards/herz.png
pelmanism/cards/insel.png
pelmanism/cards/kaffeekanne.png
pelmanism/cards/kaktus.png
pelmanism/cards/karos.png
pelmanism/cards/kerze.png
pelmanism/cards/kinderwagen.png
pelmanism/cards/kirche.png
pelmanism/cards/kirschen.png
pelmanism/cards/kleeblatt.png
pelmanism/cards/korb.png
pelmanism/cards/kreis.png
pelmanism/cards/laster.png
pelmanism/cards/laterne.png
pelmanism/cards/lokomotive.png
pelmanism/cards/mond.png
pelmanism/cards/pilze.png
pelmanism/cards/quadrate.png
pelmanism/cards/rohr.png
pelmanism/cards/saege.png
pelmanism/cards/schiff.png
pelmanism/cards/schildkroete.png
pelmanism/cards/schrat.png
pelmanism/cards/tannen.png
pelmanism/cards/vulkan.png
pelmanism/cards/warndreieck.png
pelmanism/cards/wecker.png
pelmanism/cards/windmuehle.png
pelmanism/cards/wuerfel.png
pelmanism/cards/zange.png
pelmanism-1.1.dist-info/LICENSE
pelmanism-1.1.dist-info/METADATA
pelmanism-1.1.dist-info/WHEEL
pelmanism-1.1.dist-info/entry_points.txt
pelmanism-1.1.dist-info/top_level.txt
pelmanism-1.1.dist-info/RECORD
