Metadata-Version: 2.1
Name: pelmanism
Version: 1.1
Summary: Pelmanism Memory Game
Home-page: http://www.rolf-sander.net/software/pelmanism
Author: Rolf Sander
Author-email: mail@rolf-sander.net
License: UNKNOWN
Platform: UNKNOWN
Classifier: Programming Language :: Python :: 3.6
Classifier: License :: OSI Approved :: GNU General Public License (GPL)
Classifier: Operating System :: OS Independent
Classifier: Natural Language :: English
Classifier: Topic :: Games/Entertainment :: Board Games
Requires-Python: >=3.6
Requires-Dist: Pillow
